{
	"autociv.settings.reset.all": "false",
	"autociv.settings.autociv_readme.seen": "false",
	"autociv.lobby.chat.comments.max": 1000,
	"autociv.lobby.chat.notifications.max": 30,
	"autociv.lobby.chat.subject.hide": "flase",
	"autociv.lobby.gamelist.markStunGames": "false",
	"autociv.gamesetup.countdown.enabled": "false",
	"autociv.gamesetup.countdown.time": 5,
	"autociv.session.APM.enabled": "false",
	"autociv.session.graphics.corpses.max": 50,
	"autociv.session.APM.chart.enabled": "false",
	"autociv.session.StatusBar.NumberOfGatherers.show": "false",
	"autociv.session.snaptoedge.enabled": "true",
	"autociv.session.kill.nowarning": "false",
	"autociv.session.snaptoedgeOff.invert": "true",
	"autociv.resizebar.enabled": "true",
	"autociv.session.chatPanel.size.change": "false",
	"autociv.session.chatPanel.size": "0 130 100% 100%-240",
	"autociv.session.chatText.font.change": "false",
	"autociv.session.chatText.font": "sans-bold-stroke-14",
	"hotkey.autociv.open.test": "Ctrl+A+T",
	"hotkey.autociv.open.autociv_readme": "Shift+F4",
	"hotkey.autociv.open.autociv_settings": "F4",
	"hotkey.autociv.gamesetup.focus.chatInput": "Alt+Q",
	"hotkey.autociv.lobby.focus.chatInput": "Alt+Q",
	"hotkey.autociv.lobby.focus.gameList": "Alt+W",
	"hotkey.autociv.CLI.toggle": "Ctrl+C+L",
	"hotkey.autociv.CLI.stdout.toggle": "Alt+S",
	"hotkey.autociv.CLI.stdout.eval": "Alt+E",
	"hotkey.autociv.lobby.gameList.selected.join": "Alt+E",
	"hotkey.autociv.selection.nowoundedonly": "K",
	"hotkey.autociv.session.minimap.expand.toggle": "Shift+Tab",
	"hotkey.autociv.session.building.place.City_Wall": "Space+W",
	"hotkey.autociv.session.building.place.Wooden_Wall": "Space+E",
	"hotkey.autociv.session.building.place.Temple": "Space+T",
	"hotkey.autociv.session.building.place.Temple_of_Apedemak": "Space+T",
	"hotkey.autociv.session.building.place.Sentry_Tower": "Space+Y",
	"hotkey.autociv.session.building.place.Outpost": "Space+O",
	"hotkey.autociv.session.building.place.Greek_Outpost": "Space+O",
	"hotkey.autociv.session.building.place.Fortress": "Space+A",
	"hotkey.autociv.session.building.place.Blockhouse_Fort": "Space+A",
	"hotkey.autociv.session.building.place.Storehouse": "Space+S",
	"hotkey.autociv.session.building.place.Defense_Tower": "Space+D",
	"hotkey.autociv.session.building.place.Field": "Space+F",
	"hotkey.autociv.session.building.place.Farmstead": "Shift+Space+F",
	"hotkey.autociv.session.building.place.Dock": "Space+G",
	"hotkey.autociv.session.building.place.House": "Space+H",
	"hotkey.autociv.session.building.place.Siege_Wall": "Space+E",
	"hotkey.autociv.session.building.place.Corral": "Space+K",
	"hotkey.autociv.session.building.place.Civic_Center": "Space+C",
	"hotkey.autociv.session.building.place.Provincial_Governor": "Space+C",
	"hotkey.autociv.session.building.place.Wonder": "Space+V",
	"hotkey.autociv.session.building.place.Barracks": "Space+B",
	"hotkey.autociv.session.building.place.Blacksmith": "Space+N",
	"hotkey.autociv.session.building.place.Market": "Space+M",
	"hotkey.autociv.session.building.place.Structure": "unused",
	"hotkey.autociv.session.building.place.Civic_Structure": "unused",
	"hotkey.autociv.session.building.place.Military_Colony": "unused",
	"hotkey.autociv.session.building.place.Stoa": "unused",
	"hotkey.autociv.session.building.place.Defensive_Structure": "unused",
	"hotkey.autociv.session.building.place.Stone_Wall": "unused",
	"hotkey.autociv.session.building.place.City_Gate": "unused",
	"hotkey.autociv.session.building.place.Wall_Turret": "unused",
	"hotkey.autociv.session.building.place.Economic_Structure": "unused",
	"hotkey.autociv.session.building.place.Military_Structure": "unused",
	"hotkey.autociv.session.building.place.Archery_Range": "unused",
	"hotkey.autociv.session.building.place.Stables": "unused",
	"hotkey.autociv.session.building.place.Elephant_Stables": "unused",
	"hotkey.autociv.session.building.place.Embassy": "unused",
	"hotkey.autociv.session.building.place.Kennel": "unused",
	"hotkey.autociv.session.building.place.Siege_Workshop": "unused",
	"hotkey.autociv.session.building.place.Resource_Structure": "unused",
	"hotkey.autociv.session.building.place.Special_Building": "unused",
	"hotkey.autociv.session.building.place.Library": "unused",
	"hotkey.autociv.session.building.place.Rotary_Mill": "unused",
	"hotkey.autociv.session.building.place.Greek_Theater": "unused",
	"hotkey.autociv.session.entity.select.City_Wall": "unused",
	"hotkey.autociv.session.entity.select.Wooden_Wall": "Ctrl+E",
	"hotkey.autociv.session.entity.select.Temple": "Ctrl+T",
	"hotkey.autociv.session.entity.select.Temple_of_Apedemak": "Ctrl+T",
	"hotkey.autociv.session.entity.select.Sentry_Tower": "Ctrl+Y",
	"hotkey.autociv.session.entity.select.Outpost": "Ctrl+O",
	"hotkey.autociv.session.entity.select.Greek_Outpost": "Ctrl+O",
	"hotkey.autociv.session.entity.select.Fortress": "unused",
	"hotkey.autociv.session.entity.select.Blockhouse_Fort": "unused",
	"hotkey.autociv.session.entity.select.Storehouse": "Ctrl+V",
	"hotkey.autociv.session.entity.select.Defense_Tower": "unused",
	"hotkey.autociv.session.entity.select.Field": "Ctrl+F",
	"hotkey.autociv.session.entity.select.Farmstead": "Shift+Ctrl+F",
	"hotkey.autociv.session.entity.select.Dock": "Ctrl+G",
	"hotkey.autociv.session.entity.select.House": "Ctrl+H",
	"hotkey.autociv.session.entity.select.Siege_Wall": "Ctrl+J",
	"hotkey.autociv.session.entity.select.Corral": "Ctrl+K",
	"hotkey.autociv.session.entity.select.Civic_Center": "Ctrl+C",
	"hotkey.autociv.session.entity.select.Wonder": "unused",
	"hotkey.autociv.session.entity.select.Barracks": "Ctrl+X",
	"hotkey.autociv.session.entity.select.Blacksmith": "Ctrl+N",
	"hotkey.autociv.session.entity.select.Market": "Ctrl+M",
	"hotkey.autociv.session.entity.select.Structure": "unused",
	"hotkey.autociv.session.entity.select.Civic_Structure": "unused",
	"hotkey.autociv.session.entity.select.Military_Colony": "unused",
	"hotkey.autociv.session.entity.select.Stoa": "unused",
	"hotkey.autociv.session.entity.select.Defensive_Structure": "unused",
	"hotkey.autociv.session.entity.select.Stone_Wall": "unused",
	"hotkey.autociv.session.entity.select.City_Gate": "unused",
	"hotkey.autociv.session.entity.select.Wall_Turret": "unused",
	"hotkey.autociv.session.entity.select.Economic_Structure": "unused",
	"hotkey.autociv.session.entity.select.Military_Structure": "unused",
	"hotkey.autociv.session.entity.select.Archery_Range": "unused",
	"hotkey.autociv.session.entity.select.Stables": "unused",
	"hotkey.autociv.session.entity.select.Elephant_Stables": "unused",
	"hotkey.autociv.session.entity.select.Embassy": "unused",
	"hotkey.autociv.session.entity.select.Kennel": "unused",
	"hotkey.autociv.session.entity.select.Siege_Workshop": "unused",
	"hotkey.autociv.session.entity.select.Resource_Structure": "unused",
	"hotkey.autociv.session.entity.select.Special_Building": "unused",
	"hotkey.autociv.session.entity.select.Library": "unused",
	"hotkey.autociv.session.entity.select.Rotary_Mill": "unused",
	"hotkey.autociv.session.entity.select.Greek_Theater": "unused",
	"hotkey.autociv.session.entity.by.class.select.Support&Worker|(Support&Elephant)": "Alt+A",
	"hotkey.autociv.session.entity.by.class.select.(Soldier|Siege|Dog)&!Ship": "Alt+S",
	"hotkey.autociv.session.entity.by.class.select.Cavalry": "Alt+E",
	"hotkey.autociv.session.entity.by.class.select.Cavalry.by.group.none": "unused",
	"hotkey.autociv.session.entity.by.class.select.Ranged": "unused",
	"hotkey.autociv.session.entity.by.class.select.Infantry": "unused",
	"hotkey.autociv.session.entity.by.class.select.Siege": "unused",
	"hotkey.autociv.session.entity.by.health.nowounded.by.class.select.Cavalry": "unused",
	"hotkey.autociv.session.entity.by.health.wounded.by.class.select.Cavalry": "unused",
	"hotkey.autociv.session.entity.by.rank.1": "unused",
	"hotkey.autociv.session.entity.by.rank.2": "unused",
	"hotkey.autociv.session.entity.by.rank.3": "unused",
	"hotkey.autociv.session.building.autotrain.enable": "Alt+Q",
	"hotkey.autociv.session.building.autotrain.disable": "Alt+W",
	"hotkey.autociv.session.production.queue.clear": "Alt+R",
	"hotkey.autociv.session.formation.set.null": "Space+1",
	"hotkey.autociv.session.formation.set.box": "Space+2",
	"hotkey.autociv.session.formation.set.column_closed": "Space+3",
	"hotkey.autociv.session.formation.set.line_closed": "Space+4",
	"hotkey.autociv.session.formation.set.column_open": "Space+5",
	"hotkey.autociv.session.formation.set.line_open": "Space+6",
	"hotkey.autociv.session.formation.set.flank": "Space+7",
	"hotkey.autociv.session.formation.set.skirmish": "Space+8",
	"hotkey.autociv.session.formation.set.wedge": "Space+9",
	"hotkey.autociv.session.formation.set.battle_line": "Space+0",
	"hotkey.autociv.session.formation.set.syntagma": "Space+'",
	"hotkey.autociv.session.formation.set.anti_cavalry": "unused",
	"hotkey.autociv.session.formation.set.phalanx": "unused",
	"hotkey.autociv.session.formation.set.scatter": "unused",
	"hotkey.autociv.session.formation.set.testudo": "unused",
	"hotkey.autociv.session.stance.set.violent": "Alt+1",
	"hotkey.autociv.session.stance.set.aggressive": "Alt+2",
	"hotkey.autociv.session.stance.set.defensive": "Alt+3",
	"hotkey.autociv.session.stance.set.passive": "Alt+4",
	"hotkey.autociv.session.stance.set.standground": "Alt+5",
	"hotkey.autociv.session.snaptoedgeOff": "Alt",
	"hotkey.autociv.group.button.garrison": "Ctrl",
	"hotkey.autociv.minimap.mode.flare": "Alt"
}
